pyke/__init__.py
pyke/__version__.py
pyke/_base_client.py
pyke/_schema/get_schema_json.py
pyke/endpoints/__init__.py
pyke/endpoints/account.py
pyke/endpoints/champion.py
pyke/endpoints/champion_mastery.py
pyke/endpoints/clash.py
pyke/endpoints/league.py
pyke/endpoints/league_exp.py
pyke/endpoints/lol_challenges.py
pyke/endpoints/lol_status.py
pyke/endpoints/match.py
pyke/endpoints/spectator.py
pyke/endpoints/summoner.py
pyke/endpoints/tournament.py
pyke/endpoints/tournament_stub.py
pyke/enums/__init__.py
pyke/enums/continent.py
pyke/enums/division.py
pyke/enums/level.py
pyke/enums/queue.py
pyke/enums/region.py
pyke/enums/tier.py
pyke/enums/type.py
pyke/exceptions.py
pyke/main.py
pyke/models/__init__.py
pyke/models/account_v1.py
pyke/models/champion_mastery_v4.py
pyke/models/champion_v3.py
pyke/models/clash_v1.py
pyke/models/league_exp_v4.py
pyke/models/league_v4.py
pyke/models/lol_challenges_v1.py
pyke/models/lol_status_v4.py
pyke/models/match_v5.py
pyke/models/spectator_v5.py
pyke/models/summoner_v4.py
pyke/models/tournament_stub_v5.py
pyke/py.typed
pyke_lol-1.3.0.dist-info/METADATA
pyke_lol-1.3.0.dist-info/WHEEL
pyke_lol-1.3.0.dist-info/licenses/LICENCE.txt
pyke_lol-1.3.0.dist-info/RECORD
