Metadata-Version: 2.4
Name: pyke-lol
Version: 1.3.0
Summary: A Riot API wrapper specifically for League of Legends.
License: MIT
License-File: LICENCE.txt
Keywords: riot api,league of legends,lol api,riot python,riot wrapper,LoL,League of Legends,Riot Games,API,REST,restful api
Author: diodemusic
Requires-Python: >=3.10
Classifier: License :: OSI Approved :: MIT License
Classifier: Programming Language :: Python :: 3
Classifier: Programming Language :: Python :: 3.10
Classifier: Programming Language :: Python :: 3.11
Classifier: Programming Language :: Python :: 3.12
Classifier: Programming Language :: Python :: 3.13
Classifier: Programming Language :: Python :: 3.14
Requires-Dist: bandit (>=1.8.6,<2.0.0)
Requires-Dist: coverage (>=7.11.0,<8.0.0)
Requires-Dist: datamodel-code-generator (>=0.34.0,<0.35.0)
Requires-Dist: mypy (>=1.18.2,<2.0.0)
Requires-Dist: pdoc (>=15.0.4,<16.0.0)
Requires-Dist: pydantic (>=2.11.10,<3.0.0)
Requires-Dist: pytest (>=8.4.2,<9.0.0)
Requires-Dist: python-dotenv (>=1.1.1,<2.0.0)
Requires-Dist: requests (>=2.32.5,<3.0.0)
